HackendUtils/__init__.py
HackendUtils/face_recognition.py
HackendUtils/json_utils.py
HackendUtils-0.0.7.dist-info/LICENSE
HackendUtils-0.0.7.dist-info/METADATA
HackendUtils-0.0.7.dist-info/WHEEL
HackendUtils-0.0.7.dist-info/top_level.txt
HackendUtils-0.0.7.dist-info/RECORD
