Metadata-Version: 2.1
Name: HackendUtils
Version: 0.0.7
Summary: utils for hackend's python projects
Home-page: https://github.com/hackendOrg/HackendPython
Author: Hackend
Author-email: office@hackend.org
License: UNKNOWN
Platform: UNKNOWN
Classifier: Programming Language :: Python :: 2
Classifier: License :: OSI Approved :: MIT License
Classifier: Operating System :: OS Independent
